pdefinder/__init__.py
pdefinder/core.py
pdefinder/main.py
pdefinder-0.1.7.dist-info/METADATA
pdefinder-0.1.7.dist-info/WHEEL
pdefinder-0.1.7.dist-info/entry_points.txt
pdefinder-0.1.7.dist-info/top_level.txt
pdefinder-0.1.7.dist-info/RECORD
