Metadata-Version: 2.4
Name: pdefinder
Version: 0.1.7
Summary: A package for discovering PDEs using data-driven techniques
Home-page: https://github.com/Amartya-Roy/pdefinder
Author: Amartya Roy
Author-email: srz248670@iitd.ac.in
Classifier: Programming Language :: Python :: 3
Classifier: License :: OSI Approved :: MIT License
Classifier: Operating System :: OS Independent
Requires-Python: >=3.6
Requires-Dist: numpy
Requires-Dist: scipy
Requires-Dist: torch
Requires-Dist: openai
Dynamic: author
Dynamic: author-email
Dynamic: classifier
Dynamic: description
Dynamic: description-content-type
Dynamic: home-page
Dynamic: requires-dist
Dynamic: requires-python
Dynamic: summary
